setup.py
SECEdgar/__init__.py
SECEdgar/crawler.py
SECEdgar/test.py
SECEdgar_alok.egg-info/PKG-INFO
SECEdgar_alok.egg-info/SOURCES.txt
SECEdgar_alok.egg-info/dependency_links.txt
SECEdgar_alok.egg-info/entry_points.txt
SECEdgar_alok.egg-info/requires.txt
SECEdgar_alok.egg-info/top_level.txt