Metadata-Version: 1.1
Name: SECEdgar-alok
Version: 0.1.5
Summary: SEC-Edgar implements a basic Sphinx crawler for downloading the                    filings. It provides an interface to extract the filing from the SEC.gov site                  You might find it most useful for tasks involving automated                   data collection of filings from SEC.gov
Home-page: https://github.com/Alok/SEC-Edgar
Author: Alok Singh
Author-email: alokbeniwal@gmail.com
License: Apache License (2.0)
Keywords: SEC,Edgar,Crawler,filings
Platform: UNKNOWN
Classifier: Environment :: Console
Classifier: License :: OSI Approved :: Apache Software License
Classifier: Operating System :: OS Independent
Classifier: Programming Language :: Python
Classifier: Topic :: Software Development :: Libraries :: Python Modules
Classifier: Programming Language :: Python :: 3.4
Classifier: Programming Language :: Python :: 3.5
Classifier: Programming Language :: Python :: 3.6
